greenbone/scap/__version__.py
greenbone/scap/cli.py
greenbone/scap/constants.py
greenbone/scap/cpe/__init__.py
greenbone/scap/cpe/cli/__init__.py
greenbone/scap/cpe/cli/download.py
greenbone/scap/cpe/cli/find.py
greenbone/scap/cpe/manager.py
greenbone/scap/cpe/models.py
greenbone/scap/cpe_match/__init__.py
greenbone/scap/cpe_match/cli/__init__.py
greenbone/scap/cpe_match/cli/db_download.py
greenbone/scap/cpe_match/cli/db_to_json.py
greenbone/scap/cpe_match/cli/json_download.py
greenbone/scap/cpe_match/cli/processor.py
greenbone/scap/cpe_match/db/__init__.py
greenbone/scap/cpe_match/db/manager.py
greenbone/scap/cpe_match/db/models.py
greenbone/scap/cpe_match/json.py
greenbone/scap/cpe_match/producer/__init__.py
greenbone/scap/cpe_match/producer/db.py
greenbone/scap/cpe_match/producer/nvd_api.py
greenbone/scap/cpe_match/worker/__init__.py
greenbone/scap/cpe_match/worker/db.py
greenbone/scap/cpe_match/worker/json.py
greenbone/scap/cve/__init__.py
greenbone/scap/cve/cli/__init__.py
greenbone/scap/cve/cli/download.py
greenbone/scap/cve/manager.py
greenbone/scap/cve/models.py
greenbone/scap/data_utils/__init__.py
greenbone/scap/data_utils/json.py
greenbone/scap/db.py
greenbone/scap/errors.py
greenbone/scap/generic_cli/__init__.py
greenbone/scap/generic_cli/processor.py
greenbone/scap/generic_cli/producer/__init__.py
greenbone/scap/generic_cli/producer/base.py
greenbone/scap/generic_cli/producer/db.py
greenbone/scap/generic_cli/producer/nvd_api.py
greenbone/scap/generic_cli/queue.py
greenbone/scap/generic_cli/worker/__init__.py
greenbone/scap/generic_cli/worker/base.py
greenbone/scap/generic_cli/worker/db.py
greenbone/scap/generic_cli/worker/json.py
greenbone/scap/timer.py
greenbone/scap/version.py
greenbone_scap-0.3.6.dist-info/LICENSE
greenbone_scap-0.3.6.dist-info/METADATA
greenbone_scap-0.3.6.dist-info/WHEEL
greenbone_scap-0.3.6.dist-info/entry_points.txt
greenbone_scap-0.3.6.dist-info/RECORD
