Metadata-Version: 2.3
Name: greenbone-scap
Version: 0.3.6
Summary: Python library for downloading CVE and CPE from NIST NVD
License: GPL-3.0-or-later
Author: Greenbone
Author-email: info@greenbone.net
Requires-Python: >=3.11,<4.0
Classifier: Development Status :: 4 - Beta
Classifier: Environment :: Console
Classifier: Intended Audience :: Developers
Classifier: License :: OSI Approved :: GNU General Public License v3 or later (GPLv3+)
Classifier: Operating System :: OS Independent
Classifier: Programming Language :: Python :: 3
Classifier: Programming Language :: Python :: 3.11
Classifier: Programming Language :: Python :: 3.12
Classifier: Programming Language :: Python :: 3.13
Classifier: Topic :: Software Development :: Libraries :: Python Modules
Requires-Dist: fastjsonschema (>=2.21.1)
Requires-Dist: pontos (>=23.12.4)
Requires-Dist: psycopg (>=3.1.13)
Requires-Dist: rich (>=13.7.1)
Requires-Dist: shtab (>=1.6.5)
Requires-Dist: sqlalchemy[asyncio] (>=2.0.28)
Requires-Dist: stamina (>=23.2.0)
